nali/__init__.py
nali/core.py
nali/enums.py
nali/exceptions.py
nali/models.py
nali/scrapers/__init__.py
nali/scrapers/base.py
nali/scrapers/template.py
nali_scraper-2025.7.6.dist-info/METADATA
nali_scraper-2025.7.6.dist-info/WHEEL
nali_scraper-2025.7.6.dist-info/licenses/LICENSE
nali_scraper-2025.7.6.dist-info/RECORD
