Metadata-Version: 2.4
Name: nali-scraper
Version: 2025.7.6
Summary: 대학별 공지사항 크롤링을 위한 통합 스크래핑 도구
Project-URL: Homepage, https://nali.wizley.io
Project-URL: Repository, https://github.com/wizley9999/nali.git
Author-email: Wizley <wizley9999@gmail.com>
Maintainer-email: Wizley <wizley9999@gmail.com>
License-Expression: MIT
License-File: LICENSE
Requires-Python: >=3.10
Requires-Dist: beautifulsoup4>=4.13.4
Requires-Dist: requests>=2.32.4
